{
  "category": "image-to-3d",
  "sort": "trending",
  "totalItems": 626,
  "fetchedItems": 30,
  "models": [
    {
      "author": "tencent",
      "id": "tencent/Hunyuan3D-2.1",
      "downloads": 37809,
      "likes": 1068,
      "pipeline_tag": "image-to-3d",
      "lastModified": "2025-10-17T10:10:42.000Z",
      "numParameters": null,
      "repoType": "model"
    },
    {
      "author": "microsoft",
      "id": "microsoft/TRELLIS.2-4B",
      "downloads": 1437275,
      "likes": 983,
      "pipeline_tag": "image-to-3d",
      "lastModified": "2025-12-27T13:21:56.000Z",
      "numParameters": null,
      "repoType": "model"
    },
    {
      "author": "TencentARC",
      "id": "TencentARC/Pixal3D",
      "downloads": 0,
      "likes": 294,
      "pipeline_tag": "image-to-3d",
      "lastModified": "2026-05-24T03:13:58.000Z",
      "numParameters": null,
      "repoType": "model"
    },
    {
      "author": "microsoft",
      "id": "microsoft/TRELLIS-image-large",
      "downloads": 1592453,
      "likes": 663,
      "pipeline_tag": "image-to-3d",
      "lastModified": "2024-12-06T16:39:24.000Z",
      "numParameters": null,
      "repoType": "model"
    },
    {
      "author": "stabilityai",
      "id": "stabilityai/stable-fast-3d",
      "downloads": 13395,
      "likes": 826,
      "pipeline_tag": "image-to-3d",
      "lastModified": "2025-04-08T16:31:08.000Z",
      "numParameters": 1006027436,
      "repoType": "model"
    },
    {
      "author": "facebook",
      "id": "facebook/VGGT-1B",
      "downloads": 324632,
      "likes": 119,
      "pipeline_tag": "image-to-3d",
      "lastModified": "2025-03-17T12:18:15.000Z",
      "numParameters": 1256537516,
      "repoType": "model"
    },
    {
      "author": "calcuis",
      "id": "calcuis/hy3d-gguf",
      "downloads": 1179,
      "likes": 37,
      "pipeline_tag": "image-to-3d",
      "lastModified": "2025-03-24T17:54:14.000Z",
      "numParameters": 1113274432,
      "repoType": "model"
    },
    {
      "author": "tencent",
      "id": "tencent/HY-World-2.0",
      "downloads": 2439,
      "likes": 680,
      "pipeline_tag": "image-to-3d",
      "lastModified": "2026-05-21T03:25:37.000Z",
      "numParameters": null,
      "repoType": "model"
    },
    {
      "author": "LMD0311",
      "id": "LMD0311/HERMES",
      "downloads": 48,
      "likes": 5,
      "pipeline_tag": "image-to-3d",
      "lastModified": "2025-08-15T11:11:21.000Z",
      "numParameters": null,
      "repoType": "model"
    },
    {
      "author": "tencent",
      "id": "tencent/Hunyuan3D-Omni",
      "downloads": 1495,
      "likes": 176,
      "pipeline_tag": "image-to-3d",
      "lastModified": "2025-10-17T10:13:36.000Z",
      "numParameters": null,
      "repoType": "model"
    },
    {
      "author": "nvidia",
      "id": "nvidia/Lyra-2.0",
      "downloads": 1178,
      "likes": 333,
      "pipeline_tag": "image-to-3d",
      "lastModified": "2026-05-11T18:34:53.000Z",
      "numParameters": null,
      "repoType": "model"
    },
    {
      "author": "ilintar",
      "id": "ilintar/trellis2-gguf",
      "downloads": 999,
      "likes": 2,
      "pipeline_tag": "image-to-3d",
      "lastModified": "2026-06-28T15:39:15.000Z",
      "numParameters": 220674162,
      "repoType": "model"
    },
    {
      "author": "naver",
      "id": "naver/MASt3R_ViTLarge_BaseDecoder_512_catmlpdpt_metric",
      "downloads": 46215,
      "likes": 20,
      "pipeline_tag": "image-to-3d",
      "lastModified": "2024-07-18T09:09:59.000Z",
      "numParameters": 688638856,
      "repoType": "model"
    },
    {
      "author": "lhmd",
      "id": "lhmd/VolSplat",
      "downloads": 0,
      "likes": 10,
      "pipeline_tag": "image-to-3d",
      "lastModified": "2026-06-18T10:26:05.000Z",
      "numParameters": null,
      "repoType": "model"
    },
    {
      "author": "apple",
      "id": "apple/Sharp",
      "downloads": 6198,
      "likes": 393,
      "pipeline_tag": "image-to-3d",
      "lastModified": "2025-12-18T17:38:39.000Z",
      "numParameters": null,
      "repoType": "model"
    },
    {
      "author": "tencent",
      "id": "tencent/HY3D-Bench",
      "downloads": 32,
      "likes": 50,
      "pipeline_tag": "image-to-3d",
      "lastModified": "2026-02-05T06:34:33.000Z",
      "numParameters": null,
      "repoType": "model"
    },
    {
      "author": "qq456cvb",
      "id": "qq456cvb/img2cad",
      "downloads": 0,
      "likes": 2,
      "pipeline_tag": "image-to-3d",
      "lastModified": "2026-02-04T23:13:07.000Z",
      "numParameters": null,
      "repoType": "model"
    },
    {
      "author": "VAST-AI",
      "id": "VAST-AI/AniGen",
      "downloads": 0,
      "likes": 14,
      "pipeline_tag": "image-to-3d",
      "lastModified": "2026-04-13T16:33:39.000Z",
      "numParameters": null,
      "repoType": "model"
    },
    {
      "author": "SeonghuJeon",
      "id": "SeonghuJeon/GLD",
      "downloads": 0,
      "likes": 7,
      "pipeline_tag": "image-to-3d",
      "lastModified": "2026-03-25T07:01:41.000Z",
      "numParameters": null,
      "repoType": "model"
    },
    {
      "author": "VAST-AI",
      "id": "VAST-AI/LegoACE",
      "downloads": 0,
      "likes": 8,
      "pipeline_tag": "image-to-3d",
      "lastModified": "2026-05-28T16:25:54.000Z",
      "numParameters": null,
      "repoType": "model"
    },
    {
      "author": "lhmd",
      "id": "lhmd/TriSplat",
      "downloads": 0,
      "likes": 15,
      "pipeline_tag": "image-to-3d",
      "lastModified": "2026-05-31T17:03:20.000Z",
      "numParameters": null,
      "repoType": "model"
    },
    {
      "author": "nvidia",
      "id": "nvidia/dvlt",
      "downloads": 548,
      "likes": 42,
      "pipeline_tag": "image-to-3d",
      "lastModified": "2026-05-30T20:37:41.000Z",
      "numParameters": 117081731,
      "repoType": "model"
    },
    {
      "author": "fernandotonon",
      "id": "fernandotonon/QtMeshEditor-models",
      "downloads": 26,
      "likes": 2,
      "pipeline_tag": "image-to-3d",
      "lastModified": "2026-07-13T12:52:13.000Z",
      "numParameters": 409252800,
      "repoType": "model"
    },
    {
      "author": "RealseeTechnology",
      "id": "RealseeTechnology/argus-realsee3d",
      "downloads": 0,
      "likes": 2,
      "pipeline_tag": "image-to-3d",
      "lastModified": "2026-07-01T04:11:53.000Z",
      "numParameters": null,
      "repoType": "model"
    },
    {
      "author": "ddalcu",
      "id": "ddalcu/Hunyuan3D-2.1-MLX-Serve-8bit",
      "downloads": 119,
      "likes": 1,
      "pipeline_tag": "image-to-3d",
      "lastModified": "2026-07-04T19:48:26.000Z",
      "numParameters": null,
      "repoType": "model"
    },
    {
      "author": "fernandotonon",
      "id": "fernandotonon/QtMeshEditor-triposr-onnx",
      "downloads": 0,
      "likes": 1,
      "pipeline_tag": "image-to-3d",
      "lastModified": "2026-07-10T17:53:25.000Z",
      "numParameters": null,
      "repoType": "model"
    },
    {
      "author": "fernandotonon",
      "id": "fernandotonon/QtMeshEditor-triposg-onnx",
      "downloads": 0,
      "likes": 1,
      "pipeline_tag": "image-to-3d",
      "lastModified": "2026-07-10T18:40:48.000Z",
      "numParameters": null,
      "repoType": "model"
    },
    {
      "author": "cvlab",
      "id": "cvlab/zero123-weights",
      "downloads": 0,
      "likes": 23,
      "pipeline_tag": "image-to-3d",
      "lastModified": "2024-09-05T04:52:46.000Z",
      "numParameters": null,
      "repoType": "model"
    },
    {
      "author": "Peng-Wang",
      "id": "Peng-Wang/ImageDream",
      "downloads": 0,
      "likes": 39,
      "pipeline_tag": "image-to-3d",
      "lastModified": "2024-04-05T21:56:48.000Z",
      "numParameters": null,
      "repoType": "model"
    },
    {
      "author": "FrozenBurning",
      "id": "FrozenBurning/SceneDreamer",
      "downloads": 0,
      "likes": 44,
      "pipeline_tag": "image-to-3d",
      "lastModified": "2023-11-30T02:35:57.000Z",
      "numParameters": null,
      "repoType": "model"
    }
  ],
  "fetchedAt": "2026-07-13T20:47:05.806Z"
}